nqrduck_broadband/__init__.py
nqrduck_broadband/broadband.py
nqrduck_broadband/controller.py
nqrduck_broadband/model.py
nqrduck_broadband/view.py
nqrduck_broadband/widget.py
nqrduck_broadband/resources/broadband.ini
nqrduck_broadband/resources/broadband_widget.ui
nqrduck_broadband-0.0.15.dist-info/METADATA
nqrduck_broadband-0.0.15.dist-info/WHEEL
nqrduck_broadband-0.0.15.dist-info/entry_points.txt
nqrduck_broadband-0.0.15.dist-info/licenses/LICENSE
nqrduck_broadband-0.0.15.dist-info/RECORD
